alyn/__init__.py
alyn/deskew.py
alyn/skew_detect.py
alyn-0.1.1.dist-info/DESCRIPTION.rst
alyn-0.1.1.dist-info/METADATA
alyn-0.1.1.dist-info/RECORD
alyn-0.1.1.dist-info/WHEEL
alyn-0.1.1.dist-info/metadata.json
alyn-0.1.1.dist-info/top_level.txt
