Metadata-Version: 2.0
Name: alyn
Version: 0.1.1
Summary: Fix skew in images
Home-page: https://github.com/kakul/Alyn.git
Author: Kakul Chandra
Author-email: kakulchandra911@gmail.com
License: MIT
Download-URL: https://github.com
Keywords: image-processing,image-deskew,deskew,rotate,text
Platform: UNKNOWN
Requires-Dist: matplotlib
Requires-Dist: numpy
Requires-Dist: scikit-image
Requires-Dist: scipy
